{"ticket":"ENG-SYNC","ts":"20260612T022216Z","open":3,"closed":55,
"closed_without_merged_pr":[{"issue":229,"merged_closing_prs":"0"},{"issue":194,"merged_closing_prs":"0"}],
"open_issues":[{"number":254,"title":"eng: heartbeat runner — deterministic round-lifecycle machine (docs/heartbeat-runner-spec-v0.md)","updatedAt":"2026-06-12T00:34:59Z"},{"number":195,"title":"eng-47: production token shards + governed v0 pretrain dispatch (launch gate GREEN 7/7)","updatedAt":"2026-06-11T12:33:40Z"},{"number":128,"title":"eng-35: P-gate live probe leg — r1w-q3-mtp boundary pair across daemon restart (HOLD for Leo dispatch order)","updatedAt":"2026-06-11T03:26:09Z"}]}
